yaraast/__init__.py
yaraast/__main__.py
yaraast/unified_parser.py
yaraast/version.py
yaraast/analysis/__init__.py
yaraast/analysis/best_practices.py
yaraast/analysis/dependency_analyzer.py
yaraast/analysis/optimization.py
yaraast/analysis/rule_analyzer.py
yaraast/analysis/string_usage.py
yaraast/ast/__init__.py
yaraast/ast/base.py
yaraast/ast/comments.py
yaraast/ast/conditions.py
yaraast/ast/expressions.py
yaraast/ast/extern.py
yaraast/ast/meta.py
yaraast/ast/modifiers.py
yaraast/ast/modules.py
yaraast/ast/operators.py
yaraast/ast/pragmas.py
yaraast/ast/rules.py
yaraast/ast/simple_nodes.py
yaraast/ast/strings.py
yaraast/builder/__init__.py
yaraast/builder/ast_transformer.py
yaraast/builder/condition_builder.py
yaraast/builder/expression_builder.py
yaraast/builder/file_builder.py
yaraast/builder/fluent_condition_builder.py
yaraast/builder/fluent_rule_builder.py
yaraast/builder/fluent_string_builder.py
yaraast/builder/hex_string_builder.py
yaraast/builder/rule_builder.py
yaraast/cli/__init__.py
yaraast/cli/ast_tools.py
yaraast/cli/main.py
yaraast/cli/simple_differ.py
yaraast/cli/commands/__init__.py
yaraast/cli/commands/analyze.py
yaraast/cli/commands/fluent.py
yaraast/cli/commands/lsp.py
yaraast/cli/commands/metrics.py
yaraast/cli/commands/optimize.py
yaraast/cli/commands/performance.py
yaraast/cli/commands/performance_check.py
yaraast/cli/commands/roundtrip.py
yaraast/cli/commands/semantic.py
yaraast/cli/commands/serialize.py
yaraast/cli/commands/validate.py
yaraast/cli/commands/workspace.py
yaraast/cli/commands/yaral.py
yaraast/cli/commands/yarax.py
yaraast/codegen/__init__.py
yaraast/codegen/advanced_generator.py
yaraast/codegen/comment_aware_generator.py
yaraast/codegen/formatting.py
yaraast/codegen/generator.py
yaraast/codegen/pretty_printer.py
yaraast/dialects/__init__.py
yaraast/evaluation/__init__.py
yaraast/evaluation/evaluator.py
yaraast/evaluation/mock_modules.py
yaraast/evaluation/string_matcher.py
yaraast/lexer/__init__.py
yaraast-0.7.dist-info/licenses/LICENSE
yaraast-0.7.dist-info/METADATA
yaraast-0.7.dist-info/WHEEL
yaraast-0.7.dist-info/entry_points.txt
yaraast-0.7.dist-info/top_level.txt
yaraast-0.7.dist-info/RECORD
