Metadata-Version: 2.4
Name: yaraast
Version: 0.7
Summary: A Python library for parsing and manipulating YARA rules using Abstract Syntax Trees
Author-email: Marc Rivero <mriverolopez@gmail.com>
License: MIT
Classifier: Development Status :: 3 - Alpha
Classifier: Intended Audience :: Developers
Classifier: License :: OSI Approved :: MIT License
Classifier: Programming Language :: Python :: 3
Classifier: Programming Language :: Python :: 3.13
Classifier: Topic :: Security
Classifier: Topic :: Software Development :: Libraries :: Python Modules
Requires-Python: >=3.13
License-File: LICENSE
Requires-Dist: click>=8.1.0
Requires-Dist: rich>=13.0.0
Requires-Dist: attrs>=23.0.0
Requires-Dist: PyYAML>=6.0.0
Provides-Extra: lsp
Requires-Dist: pygls>=1.3.0; extra == "lsp"
Requires-Dist: lsprotocol>=2023.0.0; extra == "lsp"
Provides-Extra: dev
Requires-Dist: pytest>=7.4.0; extra == "dev"
Requires-Dist: pytest-cov>=4.1.0; extra == "dev"
Requires-Dist: pytest-xdist>=3.0.0; extra == "dev"
Requires-Dist: hypothesis>=6.0.0; extra == "dev"
Requires-Dist: black>=23.0.0; extra == "dev"
Requires-Dist: isort>=5.12.0; extra == "dev"
Requires-Dist: flake8>=7.0.0; extra == "dev"
Requires-Dist: flake8-docstrings>=1.7.0; extra == "dev"
Requires-Dist: flake8-bugbear>=23.0.0; extra == "dev"
Requires-Dist: flake8-comprehensions>=3.14.0; extra == "dev"
Requires-Dist: flake8-simplify>=0.20.0; extra == "dev"
Requires-Dist: ruff>=0.1.0; extra == "dev"
Requires-Dist: mypy>=1.8.0; extra == "dev"
Requires-Dist: bandit>=1.7.0; extra == "dev"
Requires-Dist: pre-commit>=3.0.0; extra == "dev"
Requires-Dist: pydocstyle>=6.3.0; extra == "dev"
Requires-Dist: safety>=2.3.0; extra == "dev"
Requires-Dist: types-PyYAML>=6.0.0; extra == "dev"
Requires-Dist: types-requests>=2.31.0; extra == "dev"
Provides-Extra: libyara
Requires-Dist: yara-python>=4.5.0; extra == "libyara"
Provides-Extra: performance
Requires-Dist: psutil>=5.9.0; extra == "performance"
Provides-Extra: visualization
Requires-Dist: graphviz>=0.20.0; extra == "visualization"
Provides-Extra: quality
Requires-Dist: qlty>=0.1.0; extra == "quality"
Provides-Extra: all
Requires-Dist: yaraast[dev,libyara,lsp,performance,quality,visualization]; extra == "all"
Dynamic: license-file
